patchelfy/__init__.py
patchelfy/patchelfy.py
patchelfy/patchelfy_dev.py
patchelfy-0.1.dist-info/LICENSE
patchelfy-0.1.dist-info/METADATA
patchelfy-0.1.dist-info/WHEEL
patchelfy-0.1.dist-info/top_level.txt
patchelfy-0.1.dist-info/RECORD
