Metadata-Version: 2.1
Name: patchelfy
Version: 0.1
Summary: Python library to automate gdb debugging
Author: Edoardo
Project-URL: Homepage, https://github.com/Angelo942/patchelfy
Project-URL: Bug Tracker, https://github.com/Angelo942/patchelfy/issues
Classifier: Programming Language :: Python :: 3
Classifier: License :: OSI Approved :: GNU General Public License v3 (GPLv3)
Classifier: Operating System :: Unix
Requires-Python: >=3.8
License-File: LICENSE
Requires-Dist: pwntools
Requires-Dist: capstone
